bssapi_schemas/exch.py
bssapi_schemas/odata/InformationRegister/__init__.py
bssapi_schemas/odata/__init__.py
bssapi_schemas/odata/error/__init__.py
bssapi_schemas/odata/mixin/__init__.py
bssapi_schemas-0.1.7.dist-info/WHEEL
bssapi_schemas-0.1.7.dist-info/METADATA
bssapi_schemas-0.1.7.dist-info/RECORD
